hasoffers/__init__.py
hasoffers/api.py
hasoffers-0.2.1.dist-info/DESCRIPTION.rst
hasoffers-0.2.1.dist-info/METADATA
hasoffers-0.2.1.dist-info/metadata.json
hasoffers-0.2.1.dist-info/RECORD
hasoffers-0.2.1.dist-info/top_level.txt
hasoffers-0.2.1.dist-info/WHEEL
