Metadata-Version: 2.0
Name: hasoffers
Version: 0.2.1
Summary: Python low-level client for HasOffers.com. http://developers.hasoffers.com/
Home-page: https://github.com/OohlaLabs/hasoffers
Author: OohlaLabs Limited
Author-email: packages@oohlalabs.co.nz
License: MIT
Platform: UNKNOWN
Classifier: Development Status :: 5 - Production/Stable
Classifier: Environment :: Web Environment
Classifier: Intended Audience :: Developers
Classifier: Operating System :: OS Independent
Classifier: Programming Language :: Python
Classifier: Programming Language :: Python :: 2.7
Classifier: Programming Language :: Python :: 3.3
Classifier: Programming Language :: Python :: 3.4
Classifier: Topic :: Software Development :: Libraries :: Python Modules
Requires-Dist: requests
Requires-Dist: six
